setup.py
RG_distributions/Binomialdistribution.py
RG_distributions/Gaussiandistribution.py
RG_distributions/Generaldistribution.py
RG_distributions/__init__.py
RG_distributions.egg-info/PKG-INFO
RG_distributions.egg-info/SOURCES.txt
RG_distributions.egg-info/dependency_links.txt
RG_distributions.egg-info/not-zip-safe
RG_distributions.egg-info/top_level.txt